mcp/__init__.py
mcp/main.py
spice_labs_mcp-0.1.1.dist-info/licenses/LICENSE.txt
spice_labs_mcp-0.1.1.dist-info/METADATA
spice_labs_mcp-0.1.1.dist-info/WHEEL
spice_labs_mcp-0.1.1.dist-info/top_level.txt
spice_labs_mcp-0.1.1.dist-info/RECORD
