Metadata-Version: 2.4
Name: spice-labs-mcp
Version: 0.1.1
Summary: The MCP server from Spice Labs to expand on the usability of our tools
Requires-Python: >=3.10
License-File: LICENSE.txt
Requires-Dist: httpx>=0.28.1
Requires-Dist: mcp[cli]>=1.12.2
Requires-Dist: requests>=2.32.4
Dynamic: license-file
